check_tftp/__init__.py
check_tftp/__main__.py
check_tftp-0.3.2.data/scripts/check_tftp
check_tftp-0.3.2.dist-info/LICENSE
check_tftp-0.3.2.dist-info/METADATA
check_tftp-0.3.2.dist-info/WHEEL
check_tftp-0.3.2.dist-info/top_level.txt
check_tftp-0.3.2.dist-info/RECORD
