Metadata-Version: 2.1
Name: check-tftp
Version: 0.3.2
Summary: check_tftp is an Icinga2/Nagios plugin which monitors a TFTP server by downloading a file from the server and optionally verifying its contents
Home-page: https://gitlab.com/cspeterson/check_tftp
Author: Christopher Peterson
Author-email: contact@cspeterson.net
Project-URL: Bug Tracker, https://gitlab.com/cspeterson/check_tftp/issues
Classifier: Programming Language :: Python :: 3
Classifier: License :: OSI Approved :: MIT License
Classifier: Operating System :: OS Independent
Requires-Python: >=3.6
License-File: LICENSE
Requires-Dist: nagiosplugin (<2.0.0,>=1.3.3)
Requires-Dist: tftpy (<1.0.0,>=0.8.2)
